core_gps_visualization_app/__init__.py
core_gps_visualization_app/apps.py
core_gps_visualization_app/charts.py
core_gps_visualization_app/data_config.py
core_gps_visualization_app/menus.py
core_gps_visualization_app/pn_app.py
core_gps_visualization_app/settings.py
core_gps_visualization_app/tasks.py
core_gps_visualization_app/test.py
core_gps_visualization_app/urls.py
core_gps_visualization_app/components/__init__.py
core_gps_visualization_app/components/data/__init__.py
core_gps_visualization_app/components/data/api.py
core_gps_visualization_app/components/data/data_operations.py
core_gps_visualization_app/components/data/models.py
core_gps_visualization_app/components/plots/__init__.py
core_gps_visualization_app/components/plots/api.py
core_gps_visualization_app/components/plots/models.py
core_gps_visualization_app/components/plots/operations.py
core_gps_visualization_app/permissions/__init__.py
core_gps_visualization_app/permissions/discover.py
core_gps_visualization_app/permissions/rights.py
core_gps_visualization_app/static/core_gps_visualization_app/user/css/main.css
core_gps_visualization_app/static/core_gps_visualization_app/user/js/load_initial_plots.js
core_gps_visualization_app/static/core_gps_visualization_app/user/js/select_chart_form.js
core_gps_visualization_app/static/core_gps_visualization_app/user/js/select_time_range_form.js
core_gps_visualization_app/static/core_gps_visualization_app/user/js/update_chart.js
core_gps_visualization_app/templates/core_gps_visualization_app/user/gps_visualization.html
core_gps_visualization_app/utils/__init__.py
core_gps_visualization_app/utils/data_utils.py
core_gps_visualization_app/utils/parser.py
core_gps_visualization_app/views/__init__.py
core_gps_visualization_app/views/user/__init__.py
core_gps_visualization_app/views/user/ajax.py
core_gps_visualization_app/views/user/views.py
tests/__init__.py
tests/test_data_parser.py
core_gps_visualization_app-1.0.8.dist-info/LICENSE.txt
core_gps_visualization_app-1.0.8.dist-info/METADATA
core_gps_visualization_app-1.0.8.dist-info/WHEEL
core_gps_visualization_app-1.0.8.dist-info/top_level.txt
core_gps_visualization_app-1.0.8.dist-info/RECORD
