Metadata-Version: 2.1
Name: core-gps-visualization-app
Version: 1.0.8
Summary: GPS Visualization for the core project
Home-page: https://github.com/MelvinMartins/core_gps_visualization_app
Author: NIST IT Lab
Author-email: itl_inquiries@nist.gov
License: UNKNOWN
Platform: UNKNOWN
License-File: LICENSE.txt
Requires-Dist: holoviews[recommended] (==1.14.3)
Requires-Dist: bokeh (==2.3.2)
Requires-Dist: datashader (==0.13.0)
Requires-Dist: panel (==0.12.1)
Requires-Dist: julian (==0.14)
Requires-Dist: core-explore-common-app (==1.16.*)
Requires-Dist: core-main-app (==1.16.*)
